INGRID/ImportEqFiles.py
INGRID/OMFITgeqdsk.py
INGRID/__init__.py
INGRID/geometry.py
INGRID/ingrid.py
INGRID/interpol.py
INGRID/line_tracing.py
INGRID/utils.py
INGRID/gui/__init__.py
INGRID/gui/ingrid_gui.py
INGRID/topologies/__init__.py
INGRID/topologies/sf105.py
INGRID/topologies/sf135.py
INGRID/topologies/sf15.py
INGRID/topologies/sf165.py
INGRID/topologies/sf45.py
INGRID/topologies/sf75.py
INGRID/topologies/snl.py
INGRID/topologies/udn.py
INGRID-2.0.0.dist-info/LICENSE
INGRID-2.0.0.dist-info/METADATA
INGRID-2.0.0.dist-info/NOTICE
INGRID-2.0.0.dist-info/WHEEL
INGRID-2.0.0.dist-info/top_level.txt
INGRID-2.0.0.dist-info/RECORD
