Metadata-Version: 2.1
Name: INGRID
Version: 2.0.0
Summary: Tokamak edge plasma grid generator
Home-page: http://github.com/LLNL/Ingrid
Author: B. Garcia, M. Umansky, J. Guterl
Author-email: bgarci26@ucsc.edu, umansky1@llnl.gov
License: UNKNOWN
Keywords: grid,mesh,generator,tokamak,edge,plasma,efit,uedge
Platform: UNKNOWN
Classifier: Development Status :: 5 - Production/Stable
Classifier: Topic :: Software Development
Classifier: License :: OSI Approved :: MIT License
Classifier: Programming Language :: Python :: 3
Classifier: Programming Language :: Python :: 3.5
Classifier: Programming Language :: Python :: 3.6
Classifier: Programming Language :: Python :: 3.7
Classifier: Programming Language :: Python :: 3.8
Classifier: Programming Language :: Python :: 3.9
Requires-Python: >=3.5, <4
Requires-Dist: m2r2
Requires-Dist: scipy (>=1.3.1)
Requires-Dist: numpy
Requires-Dist: pyyaml
Requires-Dist: matplotlib
Requires-Dist: tk
Requires-Dist: sympy
